streamflow/plugins/unito/postgresql/__init__.py
streamflow/plugins/unito/postgresql/database.py
streamflow/plugins/unito/postgresql/plugin.py
streamflow/plugins/unito/postgresql/version.py
streamflow/plugins/unito/postgresql/schemas/postgresql.json
streamflow/plugins/unito/postgresql/schemas/postgresql.sql
streamflow_postgresql-0.0.10.dist-info/licenses/LICENSE
streamflow_postgresql-0.0.10.dist-info/METADATA
streamflow_postgresql-0.0.10.dist-info/WHEEL
streamflow_postgresql-0.0.10.dist-info/entry_points.txt
streamflow_postgresql-0.0.10.dist-info/top_level.txt
streamflow_postgresql-0.0.10.dist-info/zip-safe
streamflow_postgresql-0.0.10.dist-info/RECORD
