Metadata-Version: 2.4
Name: streamflow-postgresql
Version: 0.0.10
Summary: StreamFlow PostgreSQL plugin
Author-email: Iacopo Colonnelli <iacopo.colonnelli@unito.it>
License: LGPL-3.0-or-later
Project-URL: Package, https://pypi.org/project/streamflow-postgresql
Project-URL: Repository, https://github.com/alpha-unito/streamflow-postgresql
Classifier: Development Status :: 3 - Alpha
Classifier: License :: OSI Approved :: GNU Lesser General Public License v3 (LGPLv3)
Classifier: Intended Audience :: Developers
Classifier: Intended Audience :: Science/Research
Classifier: Operating System :: POSIX
Classifier: Operating System :: MacOS
Classifier: Programming Language :: Python
Classifier: Programming Language :: Python :: 3 :: Only
Classifier: Programming Language :: Python :: 3.10
Classifier: Programming Language :: Python :: 3.11
Classifier: Programming Language :: Python :: 3.12
Classifier: Programming Language :: Python :: 3.13
Classifier: Programming Language :: Python :: 3.14
Classifier: Topic :: Scientific/Engineering
Classifier: Topic :: System :: Distributed Computing
Requires-Python: >=3.10
License-File: LICENSE
Requires-Dist: asyncpg==0.31.0
Requires-Dist: streamflow==0.2.0.dev14
Dynamic: license-file
